odoo8_addon_stock_location_area_data-8.0.0.1.0.99.dev10-py2.7-nspkg.pth
odoo8_addon_stock_location_area_data-8.0.0.1.0.99.dev10.dist-info/METADATA
odoo8_addon_stock_location_area_data-8.0.0.1.0.99.dev10.dist-info/RECORD
odoo8_addon_stock_location_area_data-8.0.0.1.0.99.dev10.dist-info/WHEEL
odoo8_addon_stock_location_area_data-8.0.0.1.0.99.dev10.dist-info/namespace_packages.txt
odoo8_addon_stock_location_area_data-8.0.0.1.0.99.dev10.dist-info/top_level.txt
odoo_addons/stock_location_area_data/README.rst
odoo_addons/stock_location_area_data/__init__.py
odoo_addons/stock_location_area_data/__openerp__.py
odoo_addons/stock_location_area_data/data/stock_location_area_data.xml
odoo_addons/stock_location_area_data/i18n/de.po
odoo_addons/stock_location_area_data/i18n/es.po
odoo_addons/stock_location_area_data/i18n/fr.po
odoo_addons/stock_location_area_data/i18n/it.po
odoo_addons/stock_location_area_data/i18n/sl.po
odoo_addons/stock_location_area_data/i18n/stock_location_area_data.pot
odoo_addons/stock_location_area_data/static/description/icon.png
