Metadata-Version: 2.1
Name: odoo8-addon-stock-location-area-data
Version: 8.0.0.1.0.99.dev10
Summary: Add surface units of measure
Home-page: http://www.savoirfairelinux.com
Author: Savoir-faire Linux,Odoo Community Association (OCA)
Author-email: support@odoo-community.org
License: AGPL-3
Platform: UNKNOWN
Classifier: Programming Language :: Python
Classifier: Framework :: Odoo
Classifier: License :: OSI Approved :: GNU Affero General Public License v3
Requires-Python: ~=2.7
Requires-Dist: odoo (<9.0a,>=8.0a)
